vee_clean/__init__.py
vee_clean/cleaning_functions.py
vayner_clean-0.1.8.dist-info/METADATA
vayner_clean-0.1.8.dist-info/WHEEL
vayner_clean-0.1.8.dist-info/top_level.txt
vayner_clean-0.1.8.dist-info/RECORD
